<?xml version="1.0" encoding="UTF-8" ?>
<!DOCTYPE mapper PUBLIC "-//mybatis.org//DTD Mapper 3.0//EN"
        "http://mybatis.org/dtd/mybatis-3-mapper.dtd" >
<mapper namespace="com.dm.cms.sqldao.CmsTemplateMapper">
	<resultMap id="BaseResultMap" type="com.dm.cms.model.CmsTemplate">
		<!-- WARNING - @mbggenerated This element is automatically generated by 
			MyBatis Generator, do not modify. -->
		<id column="id" property="id" jdbcType="INTEGER" />
		<result column="template_name" property="templateName"
			jdbcType="VARCHAR" />
		<result column="template_path" property="templatePath"
			jdbcType="VARCHAR" />
		<result column="template_blob_id" property="templateBlobId"
			jdbcType="INTEGER" />
		<result column="create_time" property="createTime" jdbcType="TIMESTAMP" />
		<result column="create_user" property="createUser" jdbcType="INTEGER" />
		<result column="update_time" property="updateTime" jdbcType="TIMESTAMP" />
		<result column="template_type" property="templateType"
			jdbcType="VARCHAR" />
		<result column="site_name" property="siteName" jdbcType="VARCHAR" />
		<result column="site_id" property="siteId" jdbcType="INTEGER" />
	</resultMap>
	<sql id="Base_Column_List">
		<!-- WARNING - @mbggenerated This element is automatically generated by 
			MyBatis Generator, do not modify. -->
		id, template_name, template_path, template_blob_id, create_time,
		create_user, update_time,template_type,site_id
	</sql>
	<select id="selectByPrimaryKey" resultMap="BaseResultMap"
		parameterType="java.lang.Integer">
		<!-- WARNING - @mbggenerated This element is automatically generated by 
			MyBatis Generator, do not modify. -->
		select
		<include refid="Base_Column_List" />
		from cms_template
		where id = #{id,jdbcType=INTEGER}
	</select>
	<delete id="deleteByPrimaryKey" parameterType="java.lang.Integer">
		<!-- WARNING - @mbggenerated This element is automatically generated by 
			MyBatis Generator, do not modify. -->
		delete from cms_template
		where id = #{id,jdbcType=INTEGER}
	</delete>
	<insert id="insert" parameterType="com.dm.cms.model.CmsTemplate">
		<!-- WARNING - @mbggenerated This element is automatically generated by 
			MyBatis Generator, do not modify. -->
		insert into cms_template (id, template_name, template_path,
		template_blob_id, create_time, create_user,
		update_time,site_id,template_type)
		values (#{id,jdbcType=INTEGER},
		#{templateName,jdbcType=VARCHAR},
		#{templatePath,jdbcType=VARCHAR},
		#{templateBlobId,jdbcType=INTEGER}, #{createTime,jdbcType=TIMESTAMP},
		#{createUser,jdbcType=INTEGER},
		#{updateTime,jdbcType=TIMESTAMP},
		#{siteId},#{templateType})
	</insert>
	<insert id="insertSelective" parameterType="com.dm.cms.model.CmsTemplate">
		<!-- WARNING - @mbggenerated This element is automatically generated by 
			MyBatis Generator, do not modify. -->
		insert into cms_template
		<trim prefix="(" suffix=")" suffixOverrides=",">
			<if test="id != null">
				id,
			</if>
			<if test="templateName != null">
				template_name,
			</if>
			<if test="templatePath != null">
				template_path,
			</if>
			<if test="templateBlobId != null">
				template_blob_id,
			</if>
			<if test="createTime != null">
				create_time,
			</if>
			<if test="createUser != null">
				create_user,
			</if>
			<if test="updateTime != null">
				update_time,
			</if>
			<if test="siteId !=null">
				site_id,
			</if>
			<if test="templateType!=null">
				template_type,
			</if>
		</trim>
		<trim prefix="values (" suffix=")" suffixOverrides=",">
			<if test="id != null">
				#{id,jdbcType=INTEGER},
			</if>
			<if test="templateName != null">
				#{templateName,jdbcType=VARCHAR},
			</if>
			<if test="templatePath != null">
				#{templatePath,jdbcType=VARCHAR},
			</if>
			<if test="templateBlobId != null">
				#{templateBlobId,jdbcType=INTEGER},
			</if>
			<if test="createTime != null">
				#{createTime,jdbcType=TIMESTAMP},
			</if>
			<if test="createUser != null">
				#{createUser,jdbcType=INTEGER},
			</if>
			<if test="updateTime != null">
				#{updateTime,jdbcType=TIMESTAMP},
			</if>
			<if test="siteId !=null">
				#{siteId},
			</if>
			<if test="templateType!=null">
				#{templateType},
			</if>
		</trim>
	</insert>
	<update id="updateByPrimaryKeySelective" parameterType="com.dm.cms.model.CmsTemplate">
		<!-- WARNING - @mbggenerated This element is automatically generated by 
			MyBatis Generator, do not modify. -->
		update cms_template
		<set>
			<if test="templateName != null">
				template_name = #{templateName,jdbcType=VARCHAR},
			</if>
			<if test="templatePath != null">
				template_path = #{templatePath,jdbcType=VARCHAR},
			</if>
			<if test="templateBlobId != null">
				template_blob_id = #{templateBlobId,jdbcType=INTEGER},
			</if>
			<if test="createTime != null">
				create_time = #{createTime,jdbcType=TIMESTAMP},
			</if>
			<if test="createUser != null">
				create_user = #{createUser,jdbcType=INTEGER},
			</if>
			<if test="updateTime != null">
				update_time = #{updateTime,jdbcType=TIMESTAMP},
			</if>
			<if test="siteId !=null">
				site_id = #{siteId},
			</if>
			<if test="templateType!=null">
				template_type = #{templateType},
			</if>
		</set>
		where id = #{id,jdbcType=INTEGER}
	</update>
	<update id="updateByPrimaryKey" parameterType="com.dm.cms.model.CmsTemplate">
		<!-- WARNING - @mbggenerated This element is automatically generated by 
			MyBatis Generator, do not modify. -->
		update cms_template
		set template_name =
		#{templateName,jdbcType=VARCHAR},
		template_path =
		#{templatePath,jdbcType=VARCHAR},
		template_blob_id =
		#{templateBlobId,jdbcType=INTEGER},
		create_time =
		#{createTime,jdbcType=TIMESTAMP},
		create_user =
		#{createUser,jdbcType=INTEGER},
		update_time =
		#{updateTime,jdbcType=TIMESTAMP},
		site_id = #{siteId},
		template_type = #{templateType}
		where id = #{id,jdbcType=INTEGER}
	</update>

	<select id="selectRecordsByArgMap" resultMap="BaseResultMap"
		parameterType="java.lang.Integer">
		<!-- WARNING - @mbggenerated This element is automatically generated by 
			MyBatis Generator, do not modify. -->
		select
		t0.id,t0.template_name,t0.template_path,t0.template_blob_id,t0.create_time,
		t0.create_user,t0.update_time,t0.template_type,t0.site_id,t.display_name as site_name
		from cms_template t0 left join cms_site t on site_id=t.id
		<where>
			1=1
			<if test="model != null">
				<if test="model.displayName != null">
					and t0.template_name like CONCAT(CONCAT('%',
					#{model.displayName}),'%')
				</if>
				<if test="model.dmoain != null">
					and domain like CONCAT(CONCAT('%',#{model.dmoain}),'%')
				</if>
			</if>
			<if test="siteId!=null">
				and t0.site_id=#{siteId}
			</if>
			<if test="templateType!=null">
				and t0.template_type=#{templateType}
			</if>
		</where>
		<if test="sort!=null and sort!='' ">
			ORDER BY ${sort}
		</if>
	</select>
</mapper>
